test_package/__init__.py
do_not_install_this_package-0.0.1.dist-info/LICENSE
do_not_install_this_package-0.0.1.dist-info/METADATA
do_not_install_this_package-0.0.1.dist-info/WHEEL
do_not_install_this_package-0.0.1.dist-info/top_level.txt
do_not_install_this_package-0.0.1.dist-info/RECORD
